import java.io.InputStream;
import java.io.InputStreamReader;
import java.util.Vector;
import javax.microedition.lcdui.Font;
import javax.microedition.lcdui.Graphics;

class f {
  private l a;
  
  final int b;
  
  int c;
  
  String d;
  
  String[] e;
  
  String[] f;
  
  boolean[] g;
  
  int[] h;
  
  private char[][] i;
  
  String j;
  
  String k;
  
  String l;
  
  String m;
  
  String n;
  
  String o;
  
  String[] p;
  
  String[] q;
  
  final int r;
  
  final int s;
  
  final int t;
  
  final int u;
  
  private boolean[] v;
  
  private boolean[] w;
  
  String[] x;
  
  final int y;
  
  final int z;
  
  final int A;
  
  final int B;
  
  final int C;
  
  final int D;
  
  final int E;
  
  int F;
  
  int G;
  
  final int H;
  
  int I;
  
  int J;
  
  final int K;
  
  final int L;
  
  final int M;
  
  final int N;
  
  final int O;
  
  final int P;
  
  final int Q;
  
  final int R;
  
  final int S;
  
  int T;
  
  final int U;
  
  int V;
  
  int W;
  
  final Font X;
  
  final Font Y;
  
  final int Z;
  
  int ab;
  
  int bb;
  
  int cb;
  
  int db;
  
  int eb;
  
  int fb;
  
  int gb;
  
  final int hb;
  
  int[] ib;
  
  int jb;
  
  int kb;
  
  int lb;
  
  int mb;
  
  boolean nb;
  
  boolean ob;
  
  boolean pb;
  
  int qb;
  
  int rb;
  
  int sb;
  
  int tb;
  
  int ub;
  
  int vb;
  
  int wb;
  
  final int xb;
  
  int yb;
  
  final int zb;
  
  int Ab;
  
  k Bb;
  
  Vector Cb;
  
  boolean Db;
  
  int Eb;
  
  final int Fb;
  
  final int Gb;
  
  final int Hb;
  
  final int Ib;
  
  final int Jb;
  
  final int Kb;
  
  final int Lb;
  
  final int Mb;
  
  String[] Nb;
  
  int Ob;
  
  int[] Pb;
  
  int[] Qb;
  
  long[] Rb;
  
  String Sb;
  
  String Tb;
  
  boolean Ub;
  
  boolean Vb;
  
  boolean Wb;
  
  boolean Xb;
  
  boolean Yb;
  
  int Zb;
  
  int ac;
  
  int bc;
  
  int cc;
  
  int dc;
  
  int ec;
  
  int fc;
  
  int gc;
  
  int hc;
  
  private InputStreamReader ic;
  
  private InputStream jc;
  
  final Class kc;
  
  h lc;
  
  int mc;
  
  final int nc;
  
  final int oc;
  
  boolean[] pc;
  
  String qc;
  
  char[] rc;
  
  String sc;
  
  f(l paraml) {
    // Byte code:
    //   0: getstatic JSVenice.b : Z
    //   3: istore #12
    //   5: aload_0
    //   6: invokespecial <init> : ()V
    //   9: aload_0
    //   10: sipush #512
    //   13: putfield b : I
    //   16: aload_0
    //   17: bipush #11
    //   19: putfield c : I
    //   22: aload_0
    //   23: bipush #11
    //   25: newarray boolean
    //   27: dup
    //   28: iconst_0
    //   29: iconst_1
    //   30: bastore
    //   31: dup
    //   32: iconst_1
    //   33: iconst_1
    //   34: bastore
    //   35: dup
    //   36: iconst_2
    //   37: iconst_0
    //   38: bastore
    //   39: dup
    //   40: iconst_3
    //   41: iconst_0
    //   42: bastore
    //   43: dup
    //   44: iconst_4
    //   45: iconst_0
    //   46: bastore
    //   47: dup
    //   48: iconst_5
    //   49: iconst_0
    //   50: bastore
    //   51: dup
    //   52: bipush #6
    //   54: iconst_1
    //   55: bastore
    //   56: dup
    //   57: bipush #7
    //   59: iconst_1
    //   60: bastore
    //   61: dup
    //   62: bipush #8
    //   64: iconst_0
    //   65: bastore
    //   66: dup
    //   67: bipush #9
    //   69: iconst_1
    //   70: bastore
    //   71: dup
    //   72: bipush #10
    //   74: iconst_1
    //   75: bastore
    //   76: putfield g : [Z
    //   79: aload_0
    //   80: ldc ''
    //   82: putfield j : Ljava/lang/String;
    //   85: aload_0
    //   86: ldc ''
    //   88: putfield k : Ljava/lang/String;
    //   91: aload_0
    //   92: ldc ''
    //   94: putfield l : Ljava/lang/String;
    //   97: aload_0
    //   98: ldc ''
    //   100: putfield m : Ljava/lang/String;
    //   103: aload_0
    //   104: ldc ''
    //   106: putfield n : Ljava/lang/String;
    //   109: aload_0
    //   110: ldc ''
    //   112: putfield o : Ljava/lang/String;
    //   115: aload_0
    //   116: bipush #11
    //   118: putfield r : I
    //   121: aload_0
    //   122: bipush #14
    //   124: putfield s : I
    //   127: aload_0
    //   128: bipush #17
    //   130: putfield t : I
    //   133: aload_0
    //   134: bipush #30
    //   136: putfield u : I
    //   139: aload_0
    //   140: iconst_3
    //   141: putfield y : I
    //   144: aload_0
    //   145: iconst_3
    //   146: putfield z : I
    //   149: aload_0
    //   150: bipush #20
    //   152: putfield A : I
    //   155: aload_0
    //   156: iconst_3
    //   157: putfield B : I
    //   160: aload_0
    //   161: bipush #118
    //   163: putfield C : I
    //   166: aload_0
    //   167: sipush #140
    //   170: putfield D : I
    //   173: aload_0
    //   174: bipush #6
    //   176: putfield E : I
    //   179: aload_0
    //   180: iconst_0
    //   181: putfield G : I
    //   184: aload_0
    //   185: bipush #40
    //   187: putfield H : I
    //   190: aload_0
    //   191: iconst_3
    //   192: putfield M : I
    //   195: aload_0
    //   196: bipush #35
    //   198: putfield N : I
    //   201: aload_0
    //   202: bipush #8
    //   204: putfield O : I
    //   207: aload_0
    //   208: bipush #110
    //   210: putfield P : I
    //   213: aload_0
    //   214: bipush #35
    //   216: putfield T : I
    //   219: aload_0
    //   220: bipush #100
    //   222: putfield U : I
    //   225: aload_0
    //   226: iconst_0
    //   227: putfield V : I
    //   230: aload_0
    //   231: bipush #85
    //   233: putfield W : I
    //   236: aload_0
    //   237: iconst_0
    //   238: iconst_1
    //   239: iconst_0
    //   240: invokestatic getFont : (III)Ljavax/microedition/lcdui/Font;
    //   243: putfield X : Ljavax/microedition/lcdui/Font;
    //   246: aload_0
    //   247: iconst_0
    //   248: iconst_0
    //   249: bipush #8
    //   251: invokestatic getFont : (III)Ljavax/microedition/lcdui/Font;
    //   254: putfield Y : Ljavax/microedition/lcdui/Font;
    //   257: aload_0
    //   258: iconst_5
    //   259: putfield ab : I
    //   262: aload_0
    //   263: iconst_0
    //   264: putfield cb : I
    //   267: aload_0
    //   268: iconst_0
    //   269: putfield db : I
    //   272: aload_0
    //   273: iconst_0
    //   274: putfield eb : I
    //   277: aload_0
    //   278: iconst_0
    //   279: putfield fb : I
    //   282: aload_0
    //   283: iconst_0
    //   284: putfield gb : I
    //   287: aload_0
    //   288: bipush #8
    //   290: putfield hb : I
    //   293: aload_0
    //   294: iconst_0
    //   295: putfield jb : I
    //   298: aload_0
    //   299: iconst_0
    //   300: putfield kb : I
    //   303: aload_0
    //   304: iconst_1
    //   305: putfield lb : I
    //   308: aload_0
    //   309: iconst_1
    //   310: putfield mb : I
    //   313: aload_0
    //   314: iconst_0
    //   315: putfield nb : Z
    //   318: aload_0
    //   319: iconst_0
    //   320: putfield ob : Z
    //   323: aload_0
    //   324: iconst_0
    //   325: putfield pb : Z
    //   328: aload_0
    //   329: bipush #7
    //   331: putfield qb : I
    //   334: aload_0
    //   335: bipush #35
    //   337: putfield sb : I
    //   340: aload_0
    //   341: iconst_0
    //   342: putfield vb : I
    //   345: aload_0
    //   346: iconst_0
    //   347: putfield wb : I
    //   350: aload_0
    //   351: bipush #80
    //   353: putfield xb : I
    //   356: aload_0
    //   357: iconst_0
    //   358: putfield yb : I
    //   361: aload_0
    //   362: bipush #20
    //   364: putfield zb : I
    //   367: aload_0
    //   368: iconst_0
    //   369: putfield Db : Z
    //   372: aload_0
    //   373: iconst_0
    //   374: putfield Eb : I
    //   377: aload_0
    //   378: bipush #8
    //   380: putfield Fb : I
    //   383: aload_0
    //   384: iconst_1
    //   385: putfield Gb : I
    //   388: aload_0
    //   389: iconst_2
    //   390: putfield Hb : I
    //   393: aload_0
    //   394: iconst_3
    //   395: putfield Ib : I
    //   398: aload_0
    //   399: iconst_4
    //   400: putfield Jb : I
    //   403: aload_0
    //   404: iconst_5
    //   405: putfield Kb : I
    //   408: aload_0
    //   409: bipush #14
    //   411: putfield Lb : I
    //   414: aload_0
    //   415: bipush #15
    //   417: putfield Mb : I
    //   420: aload_0
    //   421: ldc ''
    //   423: putfield Sb : Ljava/lang/String;
    //   426: aload_0
    //   427: ldc ''
    //   429: putfield Tb : Ljava/lang/String;
    //   432: aload_0
    //   433: iconst_0
    //   434: putfield Ub : Z
    //   437: aload_0
    //   438: iconst_0
    //   439: putfield Vb : Z
    //   442: aload_0
    //   443: bipush #100
    //   445: putfield Zb : I
    //   448: aload_0
    //   449: sipush #155
    //   452: putfield ac : I
    //   455: aload_0
    //   456: sipush #200
    //   459: putfield bc : I
    //   462: aload_0
    //   463: iconst_0
    //   464: putfield cc : I
    //   467: aload_0
    //   468: bipush #55
    //   470: putfield dc : I
    //   473: aload_0
    //   474: bipush #100
    //   476: putfield ec : I
    //   479: aload_0
    //   480: aload_0
    //   481: getfield Zb : I
    //   484: aload_0
    //   485: getfield cc : I
    //   488: isub
    //   489: bipush #8
    //   491: ishl
    //   492: iconst_5
    //   493: idiv
    //   494: putfield fc : I
    //   497: aload_0
    //   498: aload_0
    //   499: getfield ac : I
    //   502: aload_0
    //   503: getfield dc : I
    //   506: isub
    //   507: bipush #8
    //   509: ishl
    //   510: iconst_5
    //   511: idiv
    //   512: putfield gc : I
    //   515: aload_0
    //   516: aload_0
    //   517: getfield bc : I
    //   520: aload_0
    //   521: getfield ec : I
    //   524: isub
    //   525: bipush #8
    //   527: ishl
    //   528: iconst_5
    //   529: idiv
    //   530: putfield hc : I
    //   533: aload_0
    //   534: iconst_0
    //   535: putfield nc : I
    //   538: aload_0
    //   539: iconst_1
    //   540: putfield oc : I
    //   543: aload_0
    //   544: sipush #500
    //   547: newarray boolean
    //   549: putfield pc : [Z
    //   552: aload_0
    //   553: ldc ''
    //   555: putfield qc : Ljava/lang/String;
    //   558: aload_0
    //   559: iconst_5
    //   560: newarray char
    //   562: dup
    //   563: iconst_0
    //   564: bipush #54
    //   566: castore
    //   567: dup
    //   568: iconst_1
    //   569: bipush #50
    //   571: castore
    //   572: dup
    //   573: iconst_2
    //   574: bipush #55
    //   576: castore
    //   577: dup
    //   578: iconst_3
    //   579: bipush #48
    //   581: castore
    //   582: dup
    //   583: iconst_4
    //   584: bipush #54
    //   586: castore
    //   587: putfield rc : [C
    //   590: aload_0
    //   591: ldc 'Game Designer:\\n   Rosario Basilotta\\n\\nProject Manager:\\n   Mauro Ciucciarelli\\n\\nArt Director:\\n   Sergio D'Innocenzo\\n\\nProgrammers:\\n   Mauro Ciucciarelli\\n   Diego Polidori\\n\\nArtists:\\n   Samuela Frontini\\n   Sergio D'Innocenzo\\n'
    //   593: putfield sc : Ljava/lang/String;
    //   596: aload_0
    //   597: aload_1
    //   598: putfield a : Ll;
    //   601: aload_1
    //   602: invokevirtual e : ()V
    //   605: aload_0
    //   606: bipush #83
    //   608: putfield S : I
    //   611: aload_0
    //   612: bipush #44
    //   614: putfield Q : I
    //   617: aload_0
    //   618: sipush #132
    //   621: putfield R : I
    //   624: aload_0
    //   625: iconst_3
    //   626: newarray boolean
    //   628: putfield v : [Z
    //   631: aload_0
    //   632: iconst_3
    //   633: anewarray java/lang/String
    //   636: putfield Nb : [Ljava/lang/String;
    //   639: aload_0
    //   640: iconst_3
    //   641: newarray long
    //   643: putfield Rb : [J
    //   646: aload_0
    //   647: iconst_3
    //   648: newarray int
    //   650: putfield Pb : [I
    //   653: aload_0
    //   654: iconst_3
    //   655: newarray int
    //   657: putfield Qb : [I
    //   660: aload_0
    //   661: iconst_3
    //   662: newarray boolean
    //   664: putfield w : [Z
    //   667: aload_0
    //   668: aload_0
    //   669: getfield Y : Ljavax/microedition/lcdui/Font;
    //   672: invokevirtual getHeight : ()I
    //   675: putfield Z : I
    //   678: aload_0
    //   679: aload_0
    //   680: getfield Y : Ljavax/microedition/lcdui/Font;
    //   683: invokevirtual getHeight : ()I
    //   686: bipush #7
    //   688: imul
    //   689: iconst_5
    //   690: idiv
    //   691: putfield K : I
    //   694: aload_0
    //   695: aload_0
    //   696: getfield Y : Ljavax/microedition/lcdui/Font;
    //   699: invokevirtual getHeight : ()I
    //   702: putfield L : I
    //   705: aload_0
    //   706: aload_0
    //   707: invokevirtual getClass : ()Ljava/lang/Class;
    //   710: putfield kc : Ljava/lang/Class;
    //   713: aload_0
    //   714: aload_0
    //   715: getfield kc : Ljava/lang/Class;
    //   718: ldc 'language.dat'
    //   720: invokevirtual getResourceAsStream : (Ljava/lang/String;)Ljava/io/InputStream;
    //   723: putfield jc : Ljava/io/InputStream;
    //   726: aload_0
    //   727: new java/io/InputStreamReader
    //   730: dup
    //   731: aload_0
    //   732: getfield jc : Ljava/io/InputStream;
    //   735: invokespecial <init> : (Ljava/io/InputStream;)V
    //   738: putfield ic : Ljava/io/InputStreamReader;
    //   741: aload_0
    //   742: aload_0
    //   743: aload_0
    //   744: getfield jc : Ljava/io/InputStream;
    //   747: invokevirtual a : (Ljava/io/InputStream;)Ljava/lang/String;
    //   750: putfield d : Ljava/lang/String;
    //   753: new k
    //   756: dup
    //   757: aload_0
    //   758: getfield d : Ljava/lang/String;
    //   761: bipush #10
    //   763: invokespecial <init> : (Ljava/lang/String;C)V
    //   766: astore_2
    //   767: aload_2
    //   768: invokevirtual b : ()I
    //   771: istore_3
    //   772: aload_0
    //   773: iload_3
    //   774: anewarray java/lang/String
    //   777: putfield e : [Ljava/lang/String;
    //   780: iconst_0
    //   781: istore #4
    //   783: iload #12
    //   785: ifeq -> 802
    //   788: aload_0
    //   789: getfield e : [Ljava/lang/String;
    //   792: iload #4
    //   794: aload_2
    //   795: invokevirtual c : ()Ljava/lang/String;
    //   798: aastore
    //   799: iinc #4, 1
    //   802: iload #4
    //   804: iload_3
    //   805: if_icmplt -> 788
    //   808: aload_0
    //   809: aload_0
    //   810: getfield c : I
    //   813: anewarray java/lang/String
    //   816: putfield f : [Ljava/lang/String;
    //   819: aload_0
    //   820: aload_0
    //   821: getfield c : I
    //   824: newarray int
    //   826: putfield h : [I
    //   829: iconst_0
    //   830: istore #5
    //   832: iload #12
    //   834: ifne -> 799
    //   837: iload #12
    //   839: ifeq -> 868
    //   842: aload_0
    //   843: getfield h : [I
    //   846: iload #5
    //   848: iload #5
    //   850: iastore
    //   851: aload_0
    //   852: getfield f : [Ljava/lang/String;
    //   855: iload #5
    //   857: aload_0
    //   858: getfield e : [Ljava/lang/String;
    //   861: iload #5
    //   863: aaload
    //   864: aastore
    //   865: iinc #5, 1
    //   868: iload #5
    //   870: aload_0
    //   871: getfield c : I
    //   874: if_icmplt -> 842
    //   877: aload_0
    //   878: iconst_3
    //   879: anewarray java/lang/String
    //   882: putfield q : [Ljava/lang/String;
    //   885: iconst_0
    //   886: istore #6
    //   888: iload #12
    //   890: ifne -> 865
    //   893: iload #12
    //   895: ifeq -> 918
    //   898: aload_0
    //   899: getfield q : [Ljava/lang/String;
    //   902: iload #6
    //   904: aload_0
    //   905: getfield e : [Ljava/lang/String;
    //   908: iload #6
    //   910: bipush #11
    //   912: iadd
    //   913: aaload
    //   914: aastore
    //   915: iinc #6, 1
    //   918: iload #6
    //   920: iconst_3
    //   921: if_icmplt -> 898
    //   924: bipush #30
    //   926: istore #7
    //   928: iload #12
    //   930: ifne -> 915
    //   933: iload #12
    //   935: ifeq -> 998
    //   938: ldc ''
    //   940: astore #8
    //   942: new java/lang/StringBuffer
    //   945: dup
    //   946: invokespecial <init> : ()V
    //   949: aload_0
    //   950: getfield e : [Ljava/lang/String;
    //   953: iload #7
    //   955: aaload
    //   956: invokevirtual append : (Ljava/lang/String;)Ljava/lang/StringBuffer;
    //   959: ldc '\\n'
    //   961: invokevirtual append : (Ljava/lang/String;)Ljava/lang/StringBuffer;
    //   964: invokevirtual toString : ()Ljava/lang/String;
    //   967: astore #8
    //   969: new java/lang/StringBuffer
    //   972: dup
    //   973: invokespecial <init> : ()V
    //   976: aload_0
    //   977: dup_x1
    //   978: getfield k : Ljava/lang/String;
    //   981: invokevirtual append : (Ljava/lang/String;)Ljava/lang/StringBuffer;
    //   984: aload #8
    //   986: invokevirtual append : (Ljava/lang/String;)Ljava/lang/StringBuffer;
    //   989: invokevirtual toString : ()Ljava/lang/String;
    //   992: putfield k : Ljava/lang/String;
    //   995: iinc #7, 1
    //   998: iload #7
    //   1000: iload_3
    //   1001: if_icmplt -> 938
    //   1004: aload_0
    //   1005: iconst_3
    //   1006: anewarray java/lang/String
    //   1009: putfield p : [Ljava/lang/String;
    //   1012: iconst_0
    //   1013: istore #8
    //   1015: iload #12
    //   1017: ifeq -> 1040
    //   1020: aload_0
    //   1021: getfield p : [Ljava/lang/String;
    //   1024: iload #8
    //   1026: aload_0
    //   1027: getfield e : [Ljava/lang/String;
    //   1030: iload #8
    //   1032: bipush #14
    //   1034: iadd
    //   1035: aaload
    //   1036: aastore
    //   1037: iinc #8, 1
    //   1040: iload #8
    //   1042: iconst_3
    //   1043: if_icmplt -> 1020
    //   1046: aload_0
    //   1047: aload_0
    //   1048: getfield e : [Ljava/lang/String;
    //   1051: bipush #20
    //   1053: aaload
    //   1054: putfield l : Ljava/lang/String;
    //   1057: aload_0
    //   1058: aload_0
    //   1059: getfield e : [Ljava/lang/String;
    //   1062: bipush #21
    //   1064: aaload
    //   1065: putfield m : Ljava/lang/String;
    //   1068: aload_0
    //   1069: aload_0
    //   1070: getfield e : [Ljava/lang/String;
    //   1073: bipush #22
    //   1075: aaload
    //   1076: putfield n : Ljava/lang/String;
    //   1079: aload_0
    //   1080: aload_0
    //   1081: getfield e : [Ljava/lang/String;
    //   1084: bipush #23
    //   1086: aaload
    //   1087: putfield o : Ljava/lang/String;
    //   1090: iconst_1
    //   1091: istore #9
    //   1093: iload #12
    //   1095: ifne -> 1037
    //   1098: iload #12
    //   1100: ifeq -> 1151
    //   1103: aload_0
    //   1104: getfield w : [Z
    //   1107: iload #9
    //   1109: iconst_1
    //   1110: isub
    //   1111: iload #9
    //   1113: invokestatic e : (I)Z
    //   1116: bastore
    //   1117: goto -> 1148
    //   1120: astore #10
    //   1122: getstatic java/lang/System.out : Ljava/io/PrintStream;
    //   1125: new java/lang/StringBuffer
    //   1128: dup
    //   1129: invokespecial <init> : ()V
    //   1132: ldc 'Errore opzione '
    //   1134: invokevirtual append : (Ljava/lang/String;)Ljava/lang/StringBuffer;
    //   1137: iload #9
    //   1139: invokevirtual append : (I)Ljava/lang/StringBuffer;
    //   1142: invokevirtual toString : ()Ljava/lang/String;
    //   1145: invokevirtual println : (Ljava/lang/String;)V
    //   1148: iinc #9, 1
    //   1151: iload #9
    //   1153: iconst_3
    //   1154: if_icmple -> 1103
    //   1157: aload_0
    //   1158: aload_0
    //   1159: getfield w : [Z
    //   1162: iconst_0
    //   1163: baload
    //   1164: putfield Wb : Z
    //   1167: aload_0
    //   1168: aload_0
    //   1169: getfield w : [Z
    //   1172: iconst_1
    //   1173: baload
    //   1174: putfield Xb : Z
    //   1177: aload_0
    //   1178: aload_0
    //   1179: getfield w : [Z
    //   1182: iconst_2
    //   1183: baload
    //   1184: putfield Yb : Z
    //   1187: aload_0
    //   1188: invokestatic c : ()I
    //   1191: putfield Ob : I
    //   1194: aload_0
    //   1195: iload #12
    //   1197: ifne -> 1104
    //   1200: getfield Ob : I
    //   1203: iconst_2
    //   1204: if_icmple -> 1212
    //   1207: aload_0
    //   1208: iconst_2
    //   1209: putfield Ob : I
    //   1212: aload_0
    //   1213: getfield v : [Z
    //   1216: aload_0
    //   1217: getfield Ob : I
    //   1220: iconst_1
    //   1221: bastore
    //   1222: aload_1
    //   1223: aload_0
    //   1224: getfield Ob : I
    //   1227: putfield J : I
    //   1230: goto -> 1243
    //   1233: astore #10
    //   1235: getstatic java/lang/System.out : Ljava/io/PrintStream;
    //   1238: ldc 'Errore livello o salvato'
    //   1240: invokevirtual println : (Ljava/lang/String;)V
    //   1243: iconst_0
    //   1244: istore #10
    //   1246: iload #12
    //   1248: ifeq -> 1362
    //   1251: aload_0
    //   1252: getfield Pb : [I
    //   1255: iload #10
    //   1257: iconst_3
    //   1258: iload #10
    //   1260: imul
    //   1261: invokestatic c : (I)I
    //   1264: iastore
    //   1265: aload_0
    //   1266: getfield Qb : [I
    //   1269: iload #10
    //   1271: iconst_3
    //   1272: iload #10
    //   1274: imul
    //   1275: iconst_1
    //   1276: iadd
    //   1277: invokestatic c : (I)I
    //   1280: iastore
    //   1281: aload_0
    //   1282: getfield Nb : [Ljava/lang/String;
    //   1285: iload #10
    //   1287: iconst_3
    //   1288: iload #10
    //   1290: imul
    //   1291: iconst_2
    //   1292: iadd
    //   1293: invokestatic b : (I)Ljava/lang/String;
    //   1296: aastore
    //   1297: aload_0
    //   1298: getfield Rb : [J
    //   1301: iload #10
    //   1303: aload_0
    //   1304: getfield Nb : [Ljava/lang/String;
    //   1307: iload #10
    //   1309: aaload
    //   1310: invokestatic parseInt : (Ljava/lang/String;)I
    //   1313: i2l
    //   1314: lastore
    //   1315: goto -> 1328
    //   1318: astore #11
    //   1320: getstatic java/lang/System.out : Ljava/io/PrintStream;
    //   1323: ldc 'Error'
    //   1325: invokevirtual println : (Ljava/lang/String;)V
    //   1328: goto -> 1359
    //   1331: astore #11
    //   1333: getstatic java/lang/System.out : Ljava/io/PrintStream;
    //   1336: new java/lang/StringBuffer
    //   1339: dup
    //   1340: invokespecial <init> : ()V
    //   1343: ldc 'Errore punteggio '
    //   1345: invokevirtual append : (Ljava/lang/String;)Ljava/lang/StringBuffer;
    //   1348: iload #10
    //   1350: invokevirtual append : (I)Ljava/lang/StringBuffer;
    //   1353: invokevirtual toString : ()Ljava/lang/String;
    //   1356: invokevirtual println : (Ljava/lang/String;)V
    //   1359: iinc #10, 1
    //   1362: iload #10
    //   1364: iconst_3
    //   1365: if_icmplt -> 1251
    //   1368: aload_0
    //   1369: aload_1
    //   1370: getfield b : I
    //   1373: aload_0
    //   1374: getfield F : I
    //   1377: iconst_1
    //   1378: isub
    //   1379: aload_0
    //   1380: getfield K : I
    //   1383: imul
    //   1384: isub
    //   1385: aload_0
    //   1386: getfield X : Ljavax/microedition/lcdui/Font;
    //   1389: invokevirtual getHeight : ()I
    //   1392: isub
    //   1393: iconst_2
    //   1394: idiv
    //   1395: putfield I : I
    //   1398: aload_0
    //   1399: iload #12
    //   1401: ifne -> 1298
    //   1404: getfield I : I
    //   1407: bipush #40
    //   1409: if_icmpge -> 1418
    //   1412: aload_0
    //   1413: bipush #40
    //   1415: putfield I : I
    //   1418: aload_0
    //   1419: aload_0
    //   1420: getfield I : I
    //   1423: putfield J : I
    //   1426: aload_0
    //   1427: aload_0
    //   1428: getfield f : [Ljava/lang/String;
    //   1431: aload_0
    //   1432: getfield g : [Z
    //   1435: aload_1
    //   1436: getfield a : I
    //   1439: invokevirtual a : ([Ljava/lang/String;[ZI)V
    //   1442: aload_0
    //   1443: new h
    //   1446: dup
    //   1447: aload_1
    //   1448: ldc '014'
    //   1450: invokespecial <init> : (Ll;Ljava/lang/String;)V
    //   1453: putfield lc : Lh;
    //   1456: aload_0
    //   1457: invokevirtual e : ()V
    //   1460: aload_0
    //   1461: aconst_null
    //   1462: putfield lc : Lh;
    //   1465: invokestatic gc : ()V
    //   1468: return
    // Exception table:
    //   from	to	target	type
    //   1103	1117	1120	java/lang/Exception
    //   1187	1230	1233	java/lang/Exception
    //   1251	1328	1331	java/lang/Exception
    //   1297	1315	1318	java/lang/Exception
  }
  
  int a(String paramString, int paramInt) {
    // Byte code:
    //   0: iconst_0
    //   1: istore_3
    //   2: getstatic JSVenice.b : Z
    //   5: ifeq -> 11
    //   8: iinc #3, 1
    //   11: aload_1
    //   12: aload_0
    //   13: getfield f : [Ljava/lang/String;
    //   16: iload_3
    //   17: aaload
    //   18: if_acmpne -> 8
    //   21: iload_3
    //   22: iload_2
    //   23: if_icmpeq -> 28
    //   26: iload_3
    //   27: ireturn
    //   28: iload_2
    //   29: ireturn
  }
  
  void a() {
    this.i = null;
    a(this.f, this.g, this.a.a);
    this.lb = this.mb = 1;
    this.nb = false;
    this.Db = false;
    this.jb = this.kb = 0;
    this.Eb = 0;
  }
  
  void a(int paramInt) {
    this.Eb = paramInt;
    this.a.repaint(0, 0, this.a.a, this.a.b);
    this.a.serviceRepaints();
  }
  
  public void a(Graphics paramGraphics) {
    // Byte code:
    //   0: getstatic JSVenice.b : Z
    //   3: istore_2
    //   4: aload_1
    //   5: aload_0
    //   6: getfield X : Ljavax/microedition/lcdui/Font;
    //   9: invokevirtual setFont : (Ljavax/microedition/lcdui/Font;)V
    //   12: aload_1
    //   13: iconst_0
    //   14: iconst_0
    //   15: aload_0
    //   16: getfield a : Ll;
    //   19: getfield a : I
    //   22: aload_0
    //   23: getfield a : Ll;
    //   26: getfield b : I
    //   29: invokevirtual setClip : (IIII)V
    //   32: aload_1
    //   33: sipush #217
    //   36: sipush #237
    //   39: sipush #241
    //   42: invokevirtual setColor : (III)V
    //   45: aload_1
    //   46: iconst_0
    //   47: iconst_0
    //   48: aload_0
    //   49: getfield a : Ll;
    //   52: getfield a : I
    //   55: aload_0
    //   56: getfield a : Ll;
    //   59: getfield b : I
    //   62: invokevirtual fillRect : (IIII)V
    //   65: aload_0
    //   66: getfield a : Ll;
    //   69: aload_1
    //   70: iconst_0
    //   71: aload_0
    //   72: getfield a : Ll;
    //   75: getfield a : I
    //   78: aload_0
    //   79: getfield a : Ll;
    //   82: getfield Cb : [[I
    //   85: iconst_0
    //   86: aaload
    //   87: iconst_3
    //   88: iaload
    //   89: isub
    //   90: iconst_2
    //   91: idiv
    //   92: iconst_2
    //   93: invokevirtual a : (Ljavax/microedition/lcdui/Graphics;III)V
    //   96: aload_0
    //   97: getfield mc : I
    //   100: ifne -> 229
    //   103: aload_0
    //   104: getfield Db : Z
    //   107: ifeq -> 192
    //   110: aload_1
    //   111: aload_0
    //   112: getfield Zb : I
    //   115: aload_0
    //   116: getfield ac : I
    //   119: aload_0
    //   120: getfield bc : I
    //   123: invokevirtual setColor : (III)V
    //   126: aload_1
    //   127: ldc 'Loading...'
    //   129: bipush #15
    //   131: bipush #75
    //   133: bipush #20
    //   135: invokevirtual drawString : (Ljava/lang/String;III)V
    //   138: aload_1
    //   139: new java/lang/StringBuffer
    //   142: dup
    //   143: invokespecial <init> : ()V
    //   146: ldc ' '
    //   148: invokevirtual append : (Ljava/lang/String;)Ljava/lang/StringBuffer;
    //   151: aload_0
    //   152: getfield Eb : I
    //   155: invokevirtual append : (I)Ljava/lang/StringBuffer;
    //   158: ldc ' %'
    //   160: invokevirtual append : (Ljava/lang/String;)Ljava/lang/StringBuffer;
    //   163: invokevirtual toString : ()Ljava/lang/String;
    //   166: bipush #80
    //   168: bipush #75
    //   170: bipush #20
    //   172: invokevirtual drawString : (Ljava/lang/String;III)V
    //   175: aload_0
    //   176: bipush #15
    //   178: bipush #100
    //   180: aload_0
    //   181: getfield Eb : I
    //   184: bipush #10
    //   186: idiv
    //   187: aload_1
    //   188: invokevirtual a : (IIILjavax/microedition/lcdui/Graphics;)V
    //   191: return
    //   192: aload_0
    //   193: getfield gb : I
    //   196: ifne -> 216
    //   199: aload_0
    //   200: aload_1
    //   201: aload_0
    //   202: getfield i : [[C
    //   205: aload_0
    //   206: getfield ib : [I
    //   209: invokevirtual a : (Ljavax/microedition/lcdui/Graphics;[[C[I)V
    //   212: iload_2
    //   213: ifeq -> 269
    //   216: aload_0
    //   217: aload_1
    //   218: aload_0
    //   219: getfield gb : I
    //   222: invokevirtual a : (Ljavax/microedition/lcdui/Graphics;I)V
    //   225: iload_2
    //   226: ifeq -> 269
    //   229: aload_0
    //   230: getfield mc : I
    //   233: iconst_1
    //   234: if_icmpne -> 269
    //   237: aload_1
    //   238: aload_0
    //   239: getfield Y : Ljavax/microedition/lcdui/Font;
    //   242: invokevirtual setFont : (Ljavax/microedition/lcdui/Font;)V
    //   245: aload_1
    //   246: aload_0
    //   247: getfield Zb : I
    //   250: aload_0
    //   251: getfield ac : I
    //   254: aload_0
    //   255: getfield bc : I
    //   258: invokevirtual setColor : (III)V
    //   261: aload_0
    //   262: getfield lc : Lh;
    //   265: aload_1
    //   266: invokevirtual a : (Ljavax/microedition/lcdui/Graphics;)V
    //   269: return
  }
  
  public void b() {
    // Byte code:
    //   0: getstatic JSVenice.b : Z
    //   3: istore_1
    //   4: aload_0
    //   5: getfield mc : I
    //   8: iconst_1
    //   9: if_icmpne -> 19
    //   12: aload_0
    //   13: getfield lc : Lh;
    //   16: invokevirtual a : ()V
    //   19: aload_0
    //   20: getfield gb : I
    //   23: ifne -> 44
    //   26: aload_0
    //   27: aload_0
    //   28: getfield I : I
    //   31: aload_0
    //   32: getfield cb : I
    //   35: aload_0
    //   36: getfield K : I
    //   39: imul
    //   40: iadd
    //   41: putfield bb : I
    //   44: aload_0
    //   45: getfield gb : I
    //   48: iconst_5
    //   49: if_icmpeq -> 70
    //   52: aload_0
    //   53: getfield gb : I
    //   56: bipush #6
    //   58: if_icmpeq -> 70
    //   61: aload_0
    //   62: getfield gb : I
    //   65: bipush #9
    //   67: if_icmpne -> 386
    //   70: aload_0
    //   71: getfield sb : I
    //   74: aload_0
    //   75: getfield T : I
    //   78: if_icmple -> 247
    //   81: aload_0
    //   82: getfield ob : Z
    //   85: ifeq -> 247
    //   88: aload_0
    //   89: getfield vb : I
    //   92: aload_0
    //   93: getfield wb : I
    //   96: if_icmple -> 128
    //   99: aload_0
    //   100: getfield V : I
    //   103: aload_0
    //   104: getfield T : I
    //   107: iadd
    //   108: ifge -> 128
    //   111: aload_0
    //   112: iconst_0
    //   113: putfield ob : Z
    //   116: aload_0
    //   117: aload_0
    //   118: getfield wb : I
    //   121: putfield vb : I
    //   124: iload_1
    //   125: ifeq -> 386
    //   128: aload_0
    //   129: dup
    //   130: getfield sb : I
    //   133: aload_0
    //   134: getfield qb : I
    //   137: isub
    //   138: putfield sb : I
    //   141: aload_0
    //   142: dup
    //   143: getfield ub : I
    //   146: aload_0
    //   147: getfield rb : I
    //   150: iadd
    //   151: putfield ub : I
    //   154: aload_0
    //   155: getfield ub : I
    //   158: aload_0
    //   159: getfield R : I
    //   162: sipush #256
    //   165: imul
    //   166: if_icmplt -> 181
    //   169: aload_0
    //   170: aload_0
    //   171: getfield R : I
    //   174: sipush #256
    //   177: imul
    //   178: putfield ub : I
    //   181: aload_0
    //   182: aload_0
    //   183: getfield ub : I
    //   186: sipush #256
    //   189: idiv
    //   190: putfield tb : I
    //   193: aload_0
    //   194: getfield tb : I
    //   197: aload_0
    //   198: getfield R : I
    //   201: if_icmplt -> 212
    //   204: aload_0
    //   205: aload_0
    //   206: getfield R : I
    //   209: putfield tb : I
    //   212: aload_0
    //   213: getfield sb : I
    //   216: aload_0
    //   217: getfield T : I
    //   220: if_icmple -> 238
    //   223: aload_0
    //   224: getfield ub : I
    //   227: aload_0
    //   228: getfield R : I
    //   231: sipush #256
    //   234: imul
    //   235: if_icmplt -> 386
    //   238: aload_0
    //   239: iconst_0
    //   240: putfield ob : Z
    //   243: iload_1
    //   244: ifeq -> 386
    //   247: aload_0
    //   248: getfield sb : I
    //   251: aload_0
    //   252: getfield T : I
    //   255: if_icmpge -> 386
    //   258: aload_0
    //   259: getfield pb : Z
    //   262: ifeq -> 386
    //   265: aload_0
    //   266: getfield vb : I
    //   269: ifge -> 286
    //   272: aload_0
    //   273: iconst_0
    //   274: putfield pb : Z
    //   277: aload_0
    //   278: iconst_0
    //   279: putfield vb : I
    //   282: iload_1
    //   283: ifeq -> 386
    //   286: aload_0
    //   287: dup
    //   288: getfield sb : I
    //   291: aload_0
    //   292: getfield qb : I
    //   295: iadd
    //   296: putfield sb : I
    //   299: aload_0
    //   300: dup
    //   301: getfield ub : I
    //   304: aload_0
    //   305: getfield rb : I
    //   308: isub
    //   309: putfield ub : I
    //   312: aload_0
    //   313: getfield ub : I
    //   316: aload_0
    //   317: getfield Q : I
    //   320: sipush #256
    //   323: imul
    //   324: if_icmpgt -> 339
    //   327: aload_0
    //   328: aload_0
    //   329: getfield Q : I
    //   332: sipush #256
    //   335: imul
    //   336: putfield ub : I
    //   339: aload_0
    //   340: aload_0
    //   341: getfield ub : I
    //   344: sipush #256
    //   347: idiv
    //   348: putfield tb : I
    //   351: aload_0
    //   352: getfield tb : I
    //   355: aload_0
    //   356: getfield Q : I
    //   359: if_icmpgt -> 370
    //   362: aload_0
    //   363: aload_0
    //   364: getfield Q : I
    //   367: putfield tb : I
    //   370: aload_0
    //   371: getfield sb : I
    //   374: aload_0
    //   375: getfield T : I
    //   378: if_icmplt -> 386
    //   381: aload_0
    //   382: iconst_0
    //   383: putfield pb : Z
    //   386: return
  }
  
  public void b(int paramInt) {
    // Byte code:
    //   0: getstatic JSVenice.b : Z
    //   3: istore #4
    //   5: aload_0
    //   6: getfield qc : Ljava/lang/String;
    //   9: invokevirtual length : ()I
    //   12: iconst_5
    //   13: if_icmpge -> 44
    //   16: new java/lang/StringBuffer
    //   19: dup
    //   20: invokespecial <init> : ()V
    //   23: aload_0
    //   24: dup_x1
    //   25: getfield qc : Ljava/lang/String;
    //   28: invokevirtual append : (Ljava/lang/String;)Ljava/lang/StringBuffer;
    //   31: iload_1
    //   32: bipush #48
    //   34: isub
    //   35: invokevirtual append : (I)Ljava/lang/StringBuffer;
    //   38: invokevirtual toString : ()Ljava/lang/String;
    //   41: putfield qc : Ljava/lang/String;
    //   44: iconst_0
    //   45: istore_2
    //   46: aload_0
    //   47: getfield a : Ll;
    //   50: iload_1
    //   51: invokevirtual getGameAction : (I)I
    //   54: istore_2
    //   55: goto -> 59
    //   58: astore_3
    //   59: aload_0
    //   60: getfield mc : I
    //   63: iconst_1
    //   64: if_icmpne -> 76
    //   67: aload_0
    //   68: getfield lc : Lh;
    //   71: iload_1
    //   72: invokevirtual a : (I)V
    //   75: return
    //   76: aload_0
    //   77: getfield gb : I
    //   80: ifne -> 97
    //   83: aload_0
    //   84: aload_0
    //   85: getfield i : [[C
    //   88: arraylength
    //   89: putfield Ab : I
    //   92: iload #4
    //   94: ifeq -> 138
    //   97: aload_0
    //   98: getfield gb : I
    //   101: bipush #7
    //   103: if_icmpne -> 120
    //   106: aload_0
    //   107: aload_0
    //   108: getfield p : [Ljava/lang/String;
    //   111: arraylength
    //   112: putfield Ab : I
    //   115: iload #4
    //   117: ifeq -> 138
    //   120: aload_0
    //   121: getfield gb : I
    //   124: bipush #8
    //   126: if_icmpne -> 138
    //   129: aload_0
    //   130: aload_0
    //   131: getfield q : [Ljava/lang/String;
    //   134: arraylength
    //   135: putfield Ab : I
    //   138: aload_0
    //   139: aload_0
    //   140: iconst_1
    //   141: dup_x1
    //   142: putfield mb : I
    //   145: putfield lb : I
    //   148: aload_0
    //   149: iconst_0
    //   150: putfield nb : Z
    //   153: iload_2
    //   154: aload_0
    //   155: pop
    //   156: iconst_1
    //   157: if_icmpeq -> 166
    //   160: iload_1
    //   161: bipush #50
    //   163: if_icmpne -> 418
    //   166: aload_0
    //   167: getfield gb : I
    //   170: ifne -> 299
    //   173: aload_0
    //   174: dup
    //   175: getfield cb : I
    //   178: iconst_1
    //   179: isub
    //   180: putfield cb : I
    //   183: aload_0
    //   184: getfield cb : I
    //   187: ifge -> 200
    //   190: aload_0
    //   191: aload_0
    //   192: getfield Ab : I
    //   195: iconst_1
    //   196: isub
    //   197: putfield cb : I
    //   200: aload_0
    //   201: getfield Ab : I
    //   204: aload_0
    //   205: getfield F : I
    //   208: if_icmple -> 1384
    //   211: aload_0
    //   212: getfield cb : I
    //   215: aload_0
    //   216: getfield Ab : I
    //   219: iconst_1
    //   220: isub
    //   221: if_icmpne -> 256
    //   224: aload_0
    //   225: aload_0
    //   226: getfield i : [[C
    //   229: arraylength
    //   230: aload_0
    //   231: getfield F : I
    //   234: isub
    //   235: putfield G : I
    //   238: aload_0
    //   239: dup
    //   240: getfield I : I
    //   243: aload_0
    //   244: getfield G : I
    //   247: aload_0
    //   248: getfield K : I
    //   251: imul
    //   252: isub
    //   253: putfield I : I
    //   256: aload_0
    //   257: getfield cb : I
    //   260: iconst_4
    //   261: if_icmpgt -> 1384
    //   264: aload_0
    //   265: getfield G : I
    //   268: ifle -> 1384
    //   271: aload_0
    //   272: dup
    //   273: getfield G : I
    //   276: iconst_1
    //   277: isub
    //   278: putfield G : I
    //   281: aload_0
    //   282: dup
    //   283: getfield I : I
    //   286: aload_0
    //   287: getfield K : I
    //   290: iadd
    //   291: putfield I : I
    //   294: iload #4
    //   296: ifeq -> 1384
    //   299: aload_0
    //   300: getfield gb : I
    //   303: bipush #6
    //   305: if_icmpeq -> 317
    //   308: aload_0
    //   309: getfield gb : I
    //   312: bipush #9
    //   314: if_icmpne -> 360
    //   317: aload_0
    //   318: getfield vb : I
    //   321: ifle -> 1384
    //   324: aload_0
    //   325: dup
    //   326: getfield T : I
    //   329: bipush #80
    //   331: iadd
    //   332: putfield T : I
    //   335: aload_0
    //   336: iconst_1
    //   337: putfield pb : Z
    //   340: aload_0
    //   341: iconst_0
    //   342: putfield ob : Z
    //   345: aload_0
    //   346: dup
    //   347: getfield vb : I
    //   350: iconst_1
    //   351: isub
    //   352: putfield vb : I
    //   355: iload #4
    //   357: ifeq -> 1384
    //   360: aload_0
    //   361: getfield gb : I
    //   364: bipush #7
    //   366: if_icmpeq -> 378
    //   369: aload_0
    //   370: getfield gb : I
    //   373: bipush #8
    //   375: if_icmpne -> 1384
    //   378: aload_0
    //   379: dup
    //   380: getfield cb : I
    //   383: iconst_1
    //   384: isub
    //   385: putfield cb : I
    //   388: aload_0
    //   389: getfield cb : I
    //   392: ifge -> 405
    //   395: aload_0
    //   396: aload_0
    //   397: getfield Ab : I
    //   400: iconst_1
    //   401: isub
    //   402: putfield cb : I
    //   405: aload_0
    //   406: aload_0
    //   407: getfield cb : I
    //   410: putfield db : I
    //   413: iload #4
    //   415: ifeq -> 1384
    //   418: iload_2
    //   419: aload_0
    //   420: pop
    //   421: bipush #6
    //   423: if_icmpeq -> 432
    //   426: iload_1
    //   427: bipush #56
    //   429: if_icmpne -> 676
    //   432: aload_0
    //   433: getfield gb : I
    //   436: ifne -> 554
    //   439: aload_0
    //   440: dup
    //   441: getfield cb : I
    //   444: iconst_1
    //   445: iadd
    //   446: putfield cb : I
    //   449: aload_0
    //   450: getfield cb : I
    //   453: aload_0
    //   454: getfield Ab : I
    //   457: if_icmplt -> 465
    //   460: aload_0
    //   461: iconst_0
    //   462: putfield cb : I
    //   465: aload_0
    //   466: getfield Ab : I
    //   469: aload_0
    //   470: getfield F : I
    //   473: if_icmple -> 1384
    //   476: aload_0
    //   477: getfield cb : I
    //   480: ifne -> 496
    //   483: aload_0
    //   484: iconst_0
    //   485: putfield G : I
    //   488: aload_0
    //   489: aload_0
    //   490: getfield J : I
    //   493: putfield I : I
    //   496: aload_0
    //   497: getfield cb : I
    //   500: aload_0
    //   501: getfield F : I
    //   504: iconst_2
    //   505: idiv
    //   506: if_icmple -> 1384
    //   509: aload_0
    //   510: getfield i : [[C
    //   513: arraylength
    //   514: aload_0
    //   515: getfield G : I
    //   518: isub
    //   519: aload_0
    //   520: getfield F : I
    //   523: if_icmple -> 1384
    //   526: aload_0
    //   527: dup
    //   528: getfield G : I
    //   531: iconst_1
    //   532: iadd
    //   533: putfield G : I
    //   536: aload_0
    //   537: dup
    //   538: getfield I : I
    //   541: aload_0
    //   542: getfield K : I
    //   545: isub
    //   546: putfield I : I
    //   549: iload #4
    //   551: ifeq -> 1384
    //   554: aload_0
    //   555: getfield gb : I
    //   558: bipush #6
    //   560: if_icmpeq -> 572
    //   563: aload_0
    //   564: getfield gb : I
    //   567: bipush #9
    //   569: if_icmpne -> 619
    //   572: aload_0
    //   573: getfield vb : I
    //   576: aload_0
    //   577: getfield wb : I
    //   580: if_icmpge -> 1384
    //   583: aload_0
    //   584: dup
    //   585: getfield T : I
    //   588: bipush #80
    //   590: isub
    //   591: putfield T : I
    //   594: aload_0
    //   595: iconst_1
    //   596: putfield ob : Z
    //   599: aload_0
    //   600: iconst_0
    //   601: putfield pb : Z
    //   604: aload_0
    //   605: dup
    //   606: getfield vb : I
    //   609: iconst_1
    //   610: iadd
    //   611: putfield vb : I
    //   614: iload #4
    //   616: ifeq -> 1384
    //   619: aload_0
    //   620: getfield gb : I
    //   623: bipush #7
    //   625: if_icmpeq -> 637
    //   628: aload_0
    //   629: getfield gb : I
    //   632: bipush #8
    //   634: if_icmpne -> 1384
    //   637: aload_0
    //   638: dup
    //   639: getfield cb : I
    //   642: iconst_1
    //   643: iadd
    //   644: putfield cb : I
    //   647: aload_0
    //   648: getfield cb : I
    //   651: aload_0
    //   652: getfield Ab : I
    //   655: if_icmplt -> 663
    //   658: aload_0
    //   659: iconst_0
    //   660: putfield cb : I
    //   663: aload_0
    //   664: aload_0
    //   665: getfield cb : I
    //   668: putfield db : I
    //   671: iload #4
    //   673: ifeq -> 1384
    //   676: iload_2
    //   677: aload_0
    //   678: pop
    //   679: bipush #8
    //   681: if_icmpeq -> 690
    //   684: iload_1
    //   685: bipush #53
    //   687: if_icmpne -> 1338
    //   690: aload_0
    //   691: getfield gb : I
    //   694: ifne -> 1165
    //   697: aload_0
    //   698: aload_0
    //   699: getfield cb : I
    //   702: putfield fb : I
    //   705: aload_0
    //   706: aload_0
    //   707: aload_0
    //   708: getfield x : [Ljava/lang/String;
    //   711: aload_0
    //   712: getfield cb : I
    //   715: aaload
    //   716: aload_0
    //   717: getfield cb : I
    //   720: invokevirtual a : (Ljava/lang/String;I)I
    //   723: putfield eb : I
    //   726: aload_0
    //   727: getfield eb : I
    //   730: ifne -> 756
    //   733: aload_0
    //   734: new h
    //   737: dup
    //   738: aload_0
    //   739: getfield a : Ll;
    //   742: ldc '014'
    //   744: invokespecial <init> : (Ll;Ljava/lang/String;)V
    //   747: putfield lc : Lh;
    //   750: aload_0
    //   751: iconst_1
    //   752: putfield mc : I
    //   755: return
    //   756: aload_0
    //   757: getfield eb : I
    //   760: iconst_1
    //   761: if_icmpne -> 792
    //   764: aload_0
    //   765: invokevirtual d : ()V
    //   768: aload_0
    //   769: iconst_1
    //   770: putfield Db : Z
    //   773: aload_0
    //   774: getfield a : Ll;
    //   777: aload_0
    //   778: getfield Ob : I
    //   781: putfield J : I
    //   784: aload_0
    //   785: getfield a : Ll;
    //   788: invokevirtual d : ()V
    //   791: return
    //   792: aload_0
    //   793: getfield eb : I
    //   796: bipush #10
    //   798: if_icmpne -> 820
    //   801: aload_0
    //   802: invokevirtual d : ()V
    //   805: aload_0
    //   806: getfield a : Ll;
    //   809: getfield h : LJSVenice;
    //   812: invokevirtual a : ()V
    //   815: iload #4
    //   817: ifeq -> 986
    //   820: aload_0
    //   821: getfield eb : I
    //   824: iconst_2
    //   825: if_icmpne -> 836
    //   828: aload_0
    //   829: getfield a : Ll;
    //   832: invokevirtual f : ()V
    //   835: return
    //   836: aload_0
    //   837: getfield eb : I
    //   840: iconst_5
    //   841: if_icmpne -> 947
    //   844: aload_0
    //   845: new java/lang/StringBuffer
    //   848: dup
    //   849: invokespecial <init> : ()V
    //   852: aload_0
    //   853: getfield e : [Ljava/lang/String;
    //   856: bipush #17
    //   858: aaload
    //   859: invokevirtual append : (Ljava/lang/String;)Ljava/lang/StringBuffer;
    //   862: aload_0
    //   863: getfield Pb : [I
    //   866: aload_0
    //   867: getfield Ob : I
    //   870: iaload
    //   871: invokevirtual append : (I)Ljava/lang/StringBuffer;
    //   874: ldc '\\n\\n'
    //   876: invokevirtual append : (Ljava/lang/String;)Ljava/lang/StringBuffer;
    //   879: aload_0
    //   880: getfield e : [Ljava/lang/String;
    //   883: bipush #18
    //   885: aaload
    //   886: invokevirtual append : (Ljava/lang/String;)Ljava/lang/StringBuffer;
    //   889: aload_0
    //   890: getfield Qb : [I
    //   893: aload_0
    //   894: getfield Ob : I
    //   897: iaload
    //   898: invokevirtual append : (I)Ljava/lang/StringBuffer;
    //   901: ldc '\\n\\n'
    //   903: invokevirtual append : (Ljava/lang/String;)Ljava/lang/StringBuffer;
    //   906: aload_0
    //   907: getfield e : [Ljava/lang/String;
    //   910: bipush #19
    //   912: aaload
    //   913: invokevirtual append : (Ljava/lang/String;)Ljava/lang/StringBuffer;
    //   916: aload_0
    //   917: getfield Nb : [Ljava/lang/String;
    //   920: aload_0
    //   921: getfield Ob : I
    //   924: aaload
    //   925: invokevirtual append : (Ljava/lang/String;)Ljava/lang/StringBuffer;
    //   928: invokevirtual toString : ()Ljava/lang/String;
    //   931: putfield j : Ljava/lang/String;
    //   934: aload_0
    //   935: aload_0
    //   936: getfield j : Ljava/lang/String;
    //   939: invokevirtual a : (Ljava/lang/String;)V
    //   942: iload #4
    //   944: ifeq -> 986
    //   947: aload_0
    //   948: getfield eb : I
    //   951: bipush #6
    //   953: if_icmpne -> 969
    //   956: aload_0
    //   957: aload_0
    //   958: getfield k : Ljava/lang/String;
    //   961: invokevirtual a : (Ljava/lang/String;)V
    //   964: iload #4
    //   966: ifeq -> 986
    //   969: aload_0
    //   970: getfield eb : I
    //   973: bipush #9
    //   975: if_icmpne -> 986
    //   978: aload_0
    //   979: aload_0
    //   980: getfield sc : Ljava/lang/String;
    //   983: invokevirtual a : (Ljava/lang/String;)V
    //   986: aload_0
    //   987: getfield eb : I
    //   990: iconst_5
    //   991: if_icmpeq -> 1012
    //   994: aload_0
    //   995: getfield eb : I
    //   998: bipush #6
    //   1000: if_icmpeq -> 1012
    //   1003: aload_0
    //   1004: getfield eb : I
    //   1007: bipush #9
    //   1009: if_icmpne -> 1147
    //   1012: aload_0
    //   1013: aload_0
    //   1014: getfield L : I
    //   1017: aload_0
    //   1018: getfield Cb : Ljava/util/Vector;
    //   1021: invokevirtual size : ()I
    //   1024: iconst_1
    //   1025: iadd
    //   1026: imul
    //   1027: putfield V : I
    //   1030: aload_0
    //   1031: aload_0
    //   1032: bipush #35
    //   1034: dup_x1
    //   1035: putfield T : I
    //   1038: putfield sb : I
    //   1041: aload_0
    //   1042: aload_0
    //   1043: getfield Q : I
    //   1046: putfield tb : I
    //   1049: aload_0
    //   1050: aload_0
    //   1051: getfield Q : I
    //   1054: sipush #256
    //   1057: imul
    //   1058: putfield ub : I
    //   1061: aload_0
    //   1062: aload_0
    //   1063: getfield V : I
    //   1066: bipush #80
    //   1068: idiv
    //   1069: putfield wb : I
    //   1072: aload_0
    //   1073: getfield V : I
    //   1076: bipush #80
    //   1078: irem
    //   1079: istore_3
    //   1080: aload_0
    //   1081: getfield wb : I
    //   1084: iconst_1
    //   1085: if_icmple -> 1129
    //   1088: iload_3
    //   1089: bipush #50
    //   1091: if_icmpge -> 1104
    //   1094: aload_0
    //   1095: dup
    //   1096: getfield wb : I
    //   1099: iconst_1
    //   1100: isub
    //   1101: putfield wb : I
    //   1104: aload_0
    //   1105: aload_0
    //   1106: getfield qb : I
    //   1109: aload_0
    //   1110: getfield S : I
    //   1113: imul
    //   1114: sipush #256
    //   1117: imul
    //   1118: bipush #80
    //   1120: aload_0
    //   1121: getfield wb : I
    //   1124: imul
    //   1125: idiv
    //   1126: putfield rb : I
    //   1129: aload_0
    //   1130: iconst_0
    //   1131: putfield vb : I
    //   1134: aload_0
    //   1135: aload_0
    //   1136: getfield eb : I
    //   1139: putfield gb : I
    //   1142: iload #4
    //   1144: ifeq -> 1384
    //   1147: aload_0
    //   1148: aload_0
    //   1149: getfield eb : I
    //   1152: putfield gb : I
    //   1155: aload_0
    //   1156: iconst_0
    //   1157: putfield cb : I
    //   1160: iload #4
    //   1162: ifeq -> 1384
    //   1165: aload_0
    //   1166: getfield gb : I
    //   1169: iconst_2
    //   1170: if_icmpne -> 1181
    //   1173: aload_0
    //   1174: getfield a : Ll;
    //   1177: invokevirtual f : ()V
    //   1180: return
    //   1181: aload_0
    //   1182: getfield gb : I
    //   1185: bipush #7
    //   1187: if_icmpne -> 1260
    //   1190: iconst_0
    //   1191: istore_3
    //   1192: iload #4
    //   1194: ifeq -> 1207
    //   1197: aload_0
    //   1198: getfield v : [Z
    //   1201: iload_3
    //   1202: iconst_0
    //   1203: bastore
    //   1204: iinc #3, 1
    //   1207: iload_3
    //   1208: aload_0
    //   1209: getfield v : [Z
    //   1212: arraylength
    //   1213: if_icmplt -> 1197
    //   1216: aload_0
    //   1217: aload_0
    //   1218: getfield cb : I
    //   1221: putfield db : I
    //   1224: aload_0
    //   1225: getfield v : [Z
    //   1228: aload_0
    //   1229: getfield db : I
    //   1232: iconst_1
    //   1233: bastore
    //   1234: aload_0
    //   1235: getfield a : Ll;
    //   1238: aload_0
    //   1239: aload_0
    //   1240: getfield db : I
    //   1243: dup_x1
    //   1244: putfield Ob : I
    //   1247: putfield J : I
    //   1250: iload #4
    //   1252: ifne -> 1204
    //   1255: iload #4
    //   1257: ifeq -> 1384
    //   1260: aload_0
    //   1261: getfield gb : I
    //   1264: bipush #8
    //   1266: if_icmpne -> 1384
    //   1269: aload_0
    //   1270: aload_0
    //   1271: getfield cb : I
    //   1274: putfield db : I
    //   1277: aload_0
    //   1278: getfield w : [Z
    //   1281: aload_0
    //   1282: getfield db : I
    //   1285: aload_0
    //   1286: getfield w : [Z
    //   1289: aload_0
    //   1290: getfield db : I
    //   1293: baload
    //   1294: ifne -> 1301
    //   1297: iconst_1
    //   1298: goto -> 1302
    //   1301: iconst_0
    //   1302: bastore
    //   1303: aload_0
    //   1304: aload_0
    //   1305: getfield w : [Z
    //   1308: iconst_0
    //   1309: baload
    //   1310: putfield Wb : Z
    //   1313: aload_0
    //   1314: aload_0
    //   1315: getfield w : [Z
    //   1318: iconst_1
    //   1319: baload
    //   1320: putfield Xb : Z
    //   1323: aload_0
    //   1324: aload_0
    //   1325: getfield w : [Z
    //   1328: iconst_2
    //   1329: baload
    //   1330: putfield Yb : Z
    //   1333: iload #4
    //   1335: ifeq -> 1384
    //   1338: iload_1
    //   1339: bipush #-20
    //   1341: if_icmpeq -> 1350
    //   1344: iload_1
    //   1345: bipush #-6
    //   1347: if_icmpne -> 1384
    //   1350: aload_0
    //   1351: iconst_0
    //   1352: putfield gb : I
    //   1355: aload_0
    //   1356: aload_0
    //   1357: getfield fb : I
    //   1360: putfield cb : I
    //   1363: aload_0
    //   1364: aload_0
    //   1365: iconst_0
    //   1366: dup_x1
    //   1367: putfield ob : Z
    //   1370: putfield pb : Z
    //   1373: aload_0
    //   1374: iconst_0
    //   1375: putfield vb : I
    //   1378: aload_0
    //   1379: bipush #35
    //   1381: putfield T : I
    //   1384: return
    // Exception table:
    //   from	to	target	type
    //   46	55	58	java/lang/IllegalArgumentException
  }
  
  public void c() {
    this.lb = this.mb = 1;
    this.nb = false;
    this.jb = this.kb = 0;
    this.Eb = 0;
    this.Db = false;
    this.cb = 0;
  }
  
  public void a(Graphics paramGraphics, char[][] paramArrayOfchar, int[] paramArrayOfint) {
    // Byte code:
    //   0: getstatic JSVenice.b : Z
    //   3: istore #7
    //   5: aload_1
    //   6: iconst_0
    //   7: iconst_0
    //   8: aload_0
    //   9: getfield a : Ll;
    //   12: getfield a : I
    //   15: aload_0
    //   16: getfield a : Ll;
    //   19: getfield b : I
    //   22: invokevirtual setClip : (IIII)V
    //   25: aload_1
    //   26: aload_0
    //   27: getfield X : Ljavax/microedition/lcdui/Font;
    //   30: invokevirtual setFont : (Ljavax/microedition/lcdui/Font;)V
    //   33: aload_0
    //   34: getfield G : I
    //   37: istore #4
    //   39: iload #7
    //   41: ifeq -> 104
    //   44: iload #4
    //   46: aload_0
    //   47: getfield cb : I
    //   50: if_icmpeq -> 101
    //   53: aload_1
    //   54: aload_0
    //   55: getfield Zb : I
    //   58: aload_0
    //   59: getfield ac : I
    //   62: aload_0
    //   63: getfield bc : I
    //   66: invokevirtual setColor : (III)V
    //   69: aload_1
    //   70: aload_2
    //   71: iload #4
    //   73: aaload
    //   74: iconst_0
    //   75: aload_2
    //   76: iload #4
    //   78: aaload
    //   79: arraylength
    //   80: aload_3
    //   81: iload #4
    //   83: iaload
    //   84: aload_0
    //   85: getfield I : I
    //   88: iload #4
    //   90: aload_0
    //   91: getfield K : I
    //   94: imul
    //   95: iadd
    //   96: bipush #20
    //   98: invokevirtual drawChars : ([CIIIII)V
    //   101: iinc #4, 1
    //   104: iload #4
    //   106: aload_0
    //   107: getfield F : I
    //   110: aload_0
    //   111: getfield G : I
    //   114: iadd
    //   115: if_icmplt -> 44
    //   118: aload_2
    //   119: aload_0
    //   120: getfield cb : I
    //   123: aaload
    //   124: arraylength
    //   125: istore #5
    //   127: aload_0
    //   128: getfield X : Ljavax/microedition/lcdui/Font;
    //   131: aload_2
    //   132: aload_0
    //   133: getfield cb : I
    //   136: aaload
    //   137: iconst_0
    //   138: iload #5
    //   140: invokevirtual charsWidth : ([CII)I
    //   143: istore #6
    //   145: aload_1
    //   146: aload_0
    //   147: getfield Zb : I
    //   150: aload_0
    //   151: getfield ac : I
    //   154: aload_0
    //   155: getfield bc : I
    //   158: invokevirtual setColor : (III)V
    //   161: aload_1
    //   162: aload_2
    //   163: aload_0
    //   164: getfield cb : I
    //   167: aaload
    //   168: iconst_0
    //   169: iload #5
    //   171: aload_3
    //   172: aload_0
    //   173: getfield cb : I
    //   176: iaload
    //   177: aload_0
    //   178: getfield I : I
    //   181: aload_0
    //   182: getfield cb : I
    //   185: aload_0
    //   186: getfield K : I
    //   189: imul
    //   190: iadd
    //   191: bipush #20
    //   193: invokevirtual drawChars : ([CIIIII)V
    //   196: aload_1
    //   197: aload_0
    //   198: getfield Zb : I
    //   201: aload_0
    //   202: getfield fc : I
    //   205: aload_0
    //   206: getfield kb : I
    //   209: bipush #20
    //   211: idiv
    //   212: imul
    //   213: bipush #8
    //   215: ishr
    //   216: isub
    //   217: aload_0
    //   218: getfield ac : I
    //   221: aload_0
    //   222: getfield gc : I
    //   225: aload_0
    //   226: getfield kb : I
    //   229: bipush #20
    //   231: idiv
    //   232: imul
    //   233: bipush #8
    //   235: ishr
    //   236: isub
    //   237: aload_0
    //   238: getfield bc : I
    //   241: aload_0
    //   242: getfield hc : I
    //   245: aload_0
    //   246: getfield kb : I
    //   249: bipush #20
    //   251: idiv
    //   252: imul
    //   253: bipush #8
    //   255: ishr
    //   256: isub
    //   257: invokevirtual setColor : (III)V
    //   260: aload_1
    //   261: aload_2
    //   262: aload_0
    //   263: getfield cb : I
    //   266: aaload
    //   267: iconst_0
    //   268: aload_0
    //   269: getfield lb : I
    //   272: aload_3
    //   273: aload_0
    //   274: getfield cb : I
    //   277: iaload
    //   278: aload_0
    //   279: getfield I : I
    //   282: aload_0
    //   283: getfield cb : I
    //   286: aload_0
    //   287: getfield K : I
    //   290: imul
    //   291: iadd
    //   292: bipush #20
    //   294: invokevirtual drawChars : ([CIIIII)V
    //   297: aload_1
    //   298: aload_0
    //   299: getfield cc : I
    //   302: aload_0
    //   303: getfield dc : I
    //   306: aload_0
    //   307: getfield ec : I
    //   310: invokevirtual setColor : (III)V
    //   313: aload_1
    //   314: aload_2
    //   315: aload_0
    //   316: getfield cb : I
    //   319: aaload
    //   320: iconst_0
    //   321: aload_0
    //   322: getfield lb : I
    //   325: aload_3
    //   326: aload_0
    //   327: getfield cb : I
    //   330: iaload
    //   331: aload_0
    //   332: getfield I : I
    //   335: aload_0
    //   336: getfield cb : I
    //   339: aload_0
    //   340: getfield K : I
    //   343: imul
    //   344: iadd
    //   345: bipush #20
    //   347: invokevirtual drawChars : ([CIIIII)V
    //   350: aload_0
    //   351: dup
    //   352: getfield kb : I
    //   355: bipush #20
    //   357: iadd
    //   358: putfield kb : I
    //   361: aload_0
    //   362: getfield kb : I
    //   365: bipush #100
    //   367: iload #7
    //   369: ifne -> 50
    //   372: if_icmplt -> 426
    //   375: aload_0
    //   376: getfield lb : I
    //   379: iload #5
    //   381: if_icmpge -> 420
    //   384: aload_0
    //   385: dup
    //   386: getfield lb : I
    //   389: iconst_1
    //   390: iadd
    //   391: putfield lb : I
    //   394: aload_0
    //   395: getfield lb : I
    //   398: iload #5
    //   400: iconst_2
    //   401: idiv
    //   402: if_icmple -> 410
    //   405: aload_0
    //   406: iconst_1
    //   407: putfield nb : Z
    //   410: aload_0
    //   411: iconst_0
    //   412: putfield kb : I
    //   415: iload #7
    //   417: ifeq -> 426
    //   420: aload_0
    //   421: bipush #100
    //   423: putfield kb : I
    //   426: aload_0
    //   427: getfield nb : Z
    //   430: ifeq -> 661
    //   433: aload_1
    //   434: aload_0
    //   435: getfield cc : I
    //   438: aload_0
    //   439: getfield fc : I
    //   442: aload_0
    //   443: getfield jb : I
    //   446: bipush #20
    //   448: idiv
    //   449: imul
    //   450: bipush #8
    //   452: ishr
    //   453: iadd
    //   454: aload_0
    //   455: getfield dc : I
    //   458: aload_0
    //   459: getfield gc : I
    //   462: aload_0
    //   463: getfield jb : I
    //   466: bipush #20
    //   468: idiv
    //   469: imul
    //   470: bipush #8
    //   472: ishr
    //   473: iadd
    //   474: aload_0
    //   475: getfield ec : I
    //   478: aload_0
    //   479: getfield hc : I
    //   482: aload_0
    //   483: getfield jb : I
    //   486: bipush #20
    //   488: idiv
    //   489: imul
    //   490: bipush #8
    //   492: ishr
    //   493: iadd
    //   494: invokevirtual setColor : (III)V
    //   497: aload_1
    //   498: aload_2
    //   499: aload_0
    //   500: getfield cb : I
    //   503: aaload
    //   504: iconst_0
    //   505: aload_0
    //   506: getfield mb : I
    //   509: aload_3
    //   510: aload_0
    //   511: getfield cb : I
    //   514: iaload
    //   515: aload_0
    //   516: getfield I : I
    //   519: aload_0
    //   520: getfield cb : I
    //   523: aload_0
    //   524: getfield K : I
    //   527: imul
    //   528: iadd
    //   529: bipush #20
    //   531: invokevirtual drawChars : ([CIIIII)V
    //   534: aload_1
    //   535: aload_0
    //   536: getfield Zb : I
    //   539: aload_0
    //   540: getfield ac : I
    //   543: aload_0
    //   544: getfield bc : I
    //   547: invokevirtual setColor : (III)V
    //   550: aload_1
    //   551: aload_2
    //   552: aload_0
    //   553: getfield cb : I
    //   556: aaload
    //   557: iconst_0
    //   558: aload_0
    //   559: getfield mb : I
    //   562: aload_3
    //   563: aload_0
    //   564: getfield cb : I
    //   567: iaload
    //   568: aload_0
    //   569: getfield I : I
    //   572: aload_0
    //   573: getfield cb : I
    //   576: aload_0
    //   577: getfield K : I
    //   580: imul
    //   581: iadd
    //   582: bipush #20
    //   584: invokevirtual drawChars : ([CIIIII)V
    //   587: aload_0
    //   588: dup
    //   589: getfield jb : I
    //   592: bipush #20
    //   594: iadd
    //   595: putfield jb : I
    //   598: aload_0
    //   599: getfield jb : I
    //   602: bipush #100
    //   604: if_icmplt -> 661
    //   607: aload_0
    //   608: getfield mb : I
    //   611: iload #5
    //   613: if_icmpge -> 636
    //   616: aload_0
    //   617: dup
    //   618: getfield mb : I
    //   621: iconst_1
    //   622: iadd
    //   623: putfield mb : I
    //   626: aload_0
    //   627: iconst_0
    //   628: putfield jb : I
    //   631: iload #7
    //   633: ifeq -> 661
    //   636: aload_0
    //   637: iconst_0
    //   638: putfield kb : I
    //   641: aload_0
    //   642: iconst_0
    //   643: putfield jb : I
    //   646: aload_0
    //   647: aload_0
    //   648: iconst_1
    //   649: dup_x1
    //   650: putfield mb : I
    //   653: putfield lb : I
    //   656: aload_0
    //   657: iconst_0
    //   658: putfield nb : Z
    //   661: return
  }
  
  void a(Graphics paramGraphics, int paramInt) {
    // Byte code:
    //   0: getstatic JSVenice.b : Z
    //   3: istore #4
    //   5: iload_2
    //   6: bipush #10
    //   8: if_icmpeq -> 71
    //   11: iload_2
    //   12: iconst_3
    //   13: if_icmpeq -> 71
    //   16: iload_2
    //   17: iconst_4
    //   18: if_icmpeq -> 71
    //   21: aload_1
    //   22: iconst_3
    //   23: sipush #140
    //   26: bipush #30
    //   28: bipush #30
    //   30: invokevirtual setClip : (IIII)V
    //   33: aload_1
    //   34: aload_0
    //   35: getfield cc : I
    //   38: aload_0
    //   39: getfield dc : I
    //   42: aload_0
    //   43: getfield ec : I
    //   46: invokevirtual setColor : (III)V
    //   49: aload_1
    //   50: aload_0
    //   51: getfield X : Ljavax/microedition/lcdui/Font;
    //   54: invokevirtual setFont : (Ljavax/microedition/lcdui/Font;)V
    //   57: aload_1
    //   58: aload_0
    //   59: getfield n : Ljava/lang/String;
    //   62: iconst_3
    //   63: sipush #140
    //   66: bipush #20
    //   68: invokevirtual drawString : (Ljava/lang/String;III)V
    //   71: aload_1
    //   72: iconst_3
    //   73: bipush #35
    //   75: sipush #130
    //   78: bipush #100
    //   80: invokevirtual setClip : (IIII)V
    //   83: aload_1
    //   84: aload_0
    //   85: getfield Y : Ljavax/microedition/lcdui/Font;
    //   88: invokevirtual setFont : (Ljavax/microedition/lcdui/Font;)V
    //   91: aload_1
    //   92: aload_0
    //   93: getfield Zb : I
    //   96: aload_0
    //   97: getfield ac : I
    //   100: aload_0
    //   101: getfield bc : I
    //   104: invokevirtual setColor : (III)V
    //   107: iload_2
    //   108: bipush #7
    //   110: if_icmpne -> 132
    //   113: aload_0
    //   114: aload_1
    //   115: aload_0
    //   116: getfield v : [Z
    //   119: aload_0
    //   120: getfield p : [Ljava/lang/String;
    //   123: iconst_0
    //   124: invokevirtual a : (Ljavax/microedition/lcdui/Graphics;[Z[Ljava/lang/String;I)V
    //   127: iload #4
    //   129: ifeq -> 280
    //   132: iload_2
    //   133: bipush #8
    //   135: if_icmpne -> 157
    //   138: aload_0
    //   139: aload_1
    //   140: aload_0
    //   141: getfield w : [Z
    //   144: aload_0
    //   145: getfield q : [Ljava/lang/String;
    //   148: iconst_1
    //   149: invokevirtual a : (Ljavax/microedition/lcdui/Graphics;[Z[Ljava/lang/String;I)V
    //   152: iload #4
    //   154: ifeq -> 280
    //   157: iload_2
    //   158: iconst_5
    //   159: if_icmpeq -> 174
    //   162: iload_2
    //   163: bipush #6
    //   165: if_icmpeq -> 174
    //   168: iload_2
    //   169: bipush #9
    //   171: if_icmpne -> 280
    //   174: iconst_0
    //   175: istore_3
    //   176: iload #4
    //   178: ifeq -> 214
    //   181: aload_1
    //   182: aload_0
    //   183: getfield Cb : Ljava/util/Vector;
    //   186: iload_3
    //   187: invokevirtual elementAt : (I)Ljava/lang/Object;
    //   190: invokevirtual toString : ()Ljava/lang/String;
    //   193: bipush #8
    //   195: aload_0
    //   196: getfield sb : I
    //   199: aload_0
    //   200: getfield L : I
    //   203: iload_3
    //   204: imul
    //   205: iadd
    //   206: bipush #20
    //   208: invokevirtual drawString : (Ljava/lang/String;III)V
    //   211: iinc #3, 1
    //   214: iload_3
    //   215: aload_0
    //   216: getfield Cb : Ljava/util/Vector;
    //   219: invokevirtual size : ()I
    //   222: if_icmplt -> 181
    //   225: iload #4
    //   227: ifne -> 211
    //   230: aload_0
    //   231: getfield wb : I
    //   234: iconst_1
    //   235: if_icmple -> 280
    //   238: aload_0
    //   239: getfield a : Ll;
    //   242: aload_1
    //   243: iconst_1
    //   244: bipush #110
    //   246: bipush #35
    //   248: invokevirtual a : (Ljavax/microedition/lcdui/Graphics;III)V
    //   251: aload_0
    //   252: getfield a : Ll;
    //   255: aload_1
    //   256: iconst_2
    //   257: bipush #110
    //   259: sipush #139
    //   262: invokevirtual a : (Ljavax/microedition/lcdui/Graphics;III)V
    //   265: aload_0
    //   266: getfield a : Ll;
    //   269: aload_1
    //   270: iconst_3
    //   271: bipush #109
    //   273: aload_0
    //   274: getfield tb : I
    //   277: invokevirtual a : (Ljavax/microedition/lcdui/Graphics;III)V
    //   280: return
  }
  
  public void a(int paramInt1, int paramInt2, int paramInt3, Graphics paramGraphics) {
    // Byte code:
    //   0: getstatic JSVenice.b : Z
    //   3: istore #6
    //   5: iconst_0
    //   6: istore #5
    //   8: iload #6
    //   10: ifeq -> 34
    //   13: aload_0
    //   14: getfield a : Ll;
    //   17: aload #4
    //   19: iconst_5
    //   20: iload_1
    //   21: bipush #9
    //   23: iload #5
    //   25: imul
    //   26: iadd
    //   27: iload_2
    //   28: invokevirtual a : (Ljavax/microedition/lcdui/Graphics;III)V
    //   31: iinc #5, 1
    //   34: iload #5
    //   36: iload_3
    //   37: if_icmplt -> 13
    //   40: iload #6
    //   42: ifne -> 31
    //   45: return
  }
  
  public void a(Graphics paramGraphics, boolean[] paramArrayOfboolean, String[] paramArrayOfString, int paramInt) {
    // Byte code:
    //   0: getstatic JSVenice.b : Z
    //   3: istore #14
    //   5: aload_3
    //   6: arraylength
    //   7: istore #5
    //   9: bipush #90
    //   11: istore #6
    //   13: aload_1
    //   14: aload_0
    //   15: getfield Y : Ljavax/microedition/lcdui/Font;
    //   18: invokevirtual setFont : (Ljavax/microedition/lcdui/Font;)V
    //   21: aload_1
    //   22: aload_0
    //   23: getfield Zb : I
    //   26: aload_0
    //   27: getfield ac : I
    //   30: aload_0
    //   31: getfield bc : I
    //   34: invokevirtual setColor : (III)V
    //   37: iconst_0
    //   38: istore #7
    //   40: iload #14
    //   42: ifeq -> 211
    //   45: aload_1
    //   46: aload_3
    //   47: iload #7
    //   49: aaload
    //   50: bipush #8
    //   52: bipush #35
    //   54: iload #7
    //   56: aload_0
    //   57: getfield L : I
    //   60: imul
    //   61: iadd
    //   62: bipush #20
    //   64: invokevirtual drawString : (Ljava/lang/String;III)V
    //   67: aload_1
    //   68: iload #6
    //   70: bipush #35
    //   72: aload_0
    //   73: getfield L : I
    //   76: iload #7
    //   78: imul
    //   79: iadd
    //   80: bipush #8
    //   82: bipush #8
    //   84: invokevirtual drawRect : (IIII)V
    //   87: aload_2
    //   88: iload #7
    //   90: baload
    //   91: ifeq -> 208
    //   94: iload #4
    //   96: ifne -> 140
    //   99: aload_1
    //   100: new java/lang/StringBuffer
    //   103: dup
    //   104: invokespecial <init> : ()V
    //   107: aload_0
    //   108: getfield o : Ljava/lang/String;
    //   111: invokevirtual append : (Ljava/lang/String;)Ljava/lang/StringBuffer;
    //   114: iload #7
    //   116: iconst_1
    //   117: iadd
    //   118: invokevirtual append : (I)Ljava/lang/StringBuffer;
    //   121: invokevirtual toString : ()Ljava/lang/String;
    //   124: bipush #8
    //   126: bipush #35
    //   128: aload_0
    //   129: getfield L : I
    //   132: iconst_4
    //   133: imul
    //   134: iadd
    //   135: bipush #20
    //   137: invokevirtual drawString : (Ljava/lang/String;III)V
    //   140: aload_1
    //   141: iload #6
    //   143: bipush #8
    //   145: iadd
    //   146: bipush #35
    //   148: aload_0
    //   149: getfield L : I
    //   152: iload #7
    //   154: imul
    //   155: iadd
    //   156: iload #6
    //   158: bipush #35
    //   160: aload_0
    //   161: getfield L : I
    //   164: iload #7
    //   166: imul
    //   167: iadd
    //   168: bipush #8
    //   170: iadd
    //   171: invokevirtual drawLine : (IIII)V
    //   174: aload_1
    //   175: iload #6
    //   177: bipush #35
    //   179: aload_0
    //   180: getfield L : I
    //   183: iload #7
    //   185: imul
    //   186: iadd
    //   187: iload #6
    //   189: bipush #8
    //   191: iadd
    //   192: bipush #35
    //   194: aload_0
    //   195: getfield L : I
    //   198: iload #7
    //   200: imul
    //   201: iadd
    //   202: bipush #8
    //   204: iadd
    //   205: invokevirtual drawLine : (IIII)V
    //   208: iinc #7, 1
    //   211: iload #7
    //   213: iload #5
    //   215: if_icmplt -> 45
    //   218: iload #4
    //   220: iload #14
    //   222: ifne -> 91
    //   225: iconst_1
    //   226: if_icmpne -> 279
    //   229: aload_2
    //   230: aload_0
    //   231: getfield db : I
    //   234: baload
    //   235: ifeq -> 279
    //   238: aload_1
    //   239: new java/lang/StringBuffer
    //   242: dup
    //   243: invokespecial <init> : ()V
    //   246: aload_3
    //   247: aload_0
    //   248: getfield db : I
    //   251: aaload
    //   252: invokevirtual append : (Ljava/lang/String;)Ljava/lang/StringBuffer;
    //   255: ldc ' on'
    //   257: invokevirtual append : (Ljava/lang/String;)Ljava/lang/StringBuffer;
    //   260: invokevirtual toString : ()Ljava/lang/String;
    //   263: bipush #8
    //   265: bipush #35
    //   267: aload_0
    //   268: getfield L : I
    //   271: iconst_4
    //   272: imul
    //   273: iadd
    //   274: bipush #20
    //   276: invokevirtual drawString : (Ljava/lang/String;III)V
    //   279: aload_1
    //   280: iconst_0
    //   281: iconst_0
    //   282: aload_0
    //   283: getfield a : Ll;
    //   286: getfield a : I
    //   289: aload_0
    //   290: getfield a : Ll;
    //   293: getfield b : I
    //   296: invokevirtual setClip : (IIII)V
    //   299: aload_1
    //   300: aload_0
    //   301: getfield Zb : I
    //   304: aload_0
    //   305: getfield ac : I
    //   308: aload_0
    //   309: getfield bc : I
    //   312: invokevirtual setColor : (III)V
    //   315: iload #6
    //   317: bipush #8
    //   319: iadd
    //   320: iconst_3
    //   321: iadd
    //   322: istore #8
    //   324: iload #6
    //   326: bipush #16
    //   328: iadd
    //   329: iconst_3
    //   330: iadd
    //   331: istore #9
    //   333: bipush #35
    //   335: aload_0
    //   336: getfield L : I
    //   339: aload_0
    //   340: getfield cb : I
    //   343: imul
    //   344: iadd
    //   345: iconst_4
    //   346: iadd
    //   347: istore #10
    //   349: bipush #35
    //   351: aload_0
    //   352: getfield L : I
    //   355: aload_0
    //   356: getfield cb : I
    //   359: imul
    //   360: iadd
    //   361: istore #11
    //   363: bipush #35
    //   365: aload_0
    //   366: getfield L : I
    //   369: aload_0
    //   370: getfield cb : I
    //   373: imul
    //   374: iadd
    //   375: bipush #8
    //   377: iadd
    //   378: istore #12
    //   380: iload #9
    //   382: istore #13
    //   384: aload_0
    //   385: getfield a : Ll;
    //   388: aload_1
    //   389: iload #8
    //   391: iload #10
    //   393: iload #9
    //   395: iload #11
    //   397: iload #13
    //   399: iload #12
    //   401: bipush #8
    //   403: invokevirtual a : (Ljavax/microedition/lcdui/Graphics;IIIIIII)V
    //   406: return
  }
  
  public void a(String[] paramArrayOfString, boolean[] paramArrayOfboolean, int paramInt) {
    // Byte code:
    //   0: getstatic JSVenice.b : Z
    //   3: istore #9
    //   5: iconst_0
    //   6: istore #4
    //   8: iconst_0
    //   9: istore #5
    //   11: aload_2
    //   12: iconst_4
    //   13: aload_0
    //   14: getfield Ub : Z
    //   17: bastore
    //   18: iconst_0
    //   19: istore #6
    //   21: iload #9
    //   23: ifeq -> 39
    //   26: aload_2
    //   27: iload #6
    //   29: baload
    //   30: ifeq -> 36
    //   33: iinc #5, 1
    //   36: iinc #6, 1
    //   39: iload #6
    //   41: aload_2
    //   42: arraylength
    //   43: if_icmplt -> 26
    //   46: aload_0
    //   47: iload #5
    //   49: anewarray java/lang/String
    //   52: putfield x : [Ljava/lang/String;
    //   55: aload_0
    //   56: iload #5
    //   58: anewarray [C
    //   61: putfield i : [[C
    //   64: aload_0
    //   65: iload #5
    //   67: newarray int
    //   69: putfield ib : [I
    //   72: iconst_0
    //   73: istore #7
    //   75: iload #9
    //   77: ifne -> 36
    //   80: iload #9
    //   82: ifeq -> 177
    //   85: aload_2
    //   86: iload #7
    //   88: baload
    //   89: ifeq -> 174
    //   92: aload_0
    //   93: getfield i : [[C
    //   96: iload #4
    //   98: aload_1
    //   99: iload #7
    //   101: aaload
    //   102: invokevirtual length : ()I
    //   105: newarray char
    //   107: aastore
    //   108: aload_0
    //   109: getfield i : [[C
    //   112: iload #4
    //   114: aload_1
    //   115: iload #7
    //   117: aaload
    //   118: invokevirtual toCharArray : ()[C
    //   121: aastore
    //   122: aload_0
    //   123: getfield X : Ljavax/microedition/lcdui/Font;
    //   126: aload_0
    //   127: getfield i : [[C
    //   130: iload #4
    //   132: aaload
    //   133: iconst_0
    //   134: aload_0
    //   135: getfield i : [[C
    //   138: iload #4
    //   140: aaload
    //   141: arraylength
    //   142: invokevirtual charsWidth : ([CII)I
    //   145: istore #8
    //   147: aload_0
    //   148: getfield ib : [I
    //   151: iload #4
    //   153: iload_3
    //   154: iload #8
    //   156: isub
    //   157: iconst_2
    //   158: idiv
    //   159: iastore
    //   160: aload_0
    //   161: getfield x : [Ljava/lang/String;
    //   164: iload #4
    //   166: aload_1
    //   167: iload #7
    //   169: aaload
    //   170: aastore
    //   171: iinc #4, 1
    //   174: iinc #7, 1
    //   177: iload #7
    //   179: aload_1
    //   180: arraylength
    //   181: if_icmplt -> 85
    //   184: iload #5
    //   186: iload #9
    //   188: ifne -> 89
    //   191: bipush #6
    //   193: if_icmple -> 207
    //   196: aload_0
    //   197: bipush #6
    //   199: putfield F : I
    //   202: iload #9
    //   204: ifeq -> 213
    //   207: aload_0
    //   208: iload #5
    //   210: putfield F : I
    //   213: aload_0
    //   214: aload_0
    //   215: getfield a : Ll;
    //   218: getfield b : I
    //   221: aload_0
    //   222: getfield F : I
    //   225: iconst_1
    //   226: isub
    //   227: aload_0
    //   228: getfield K : I
    //   231: imul
    //   232: isub
    //   233: aload_0
    //   234: getfield X : Ljavax/microedition/lcdui/Font;
    //   237: invokevirtual getHeight : ()I
    //   240: isub
    //   241: iconst_2
    //   242: idiv
    //   243: putfield I : I
    //   246: aload_0
    //   247: getfield I : I
    //   250: bipush #40
    //   252: if_icmpge -> 261
    //   255: aload_0
    //   256: bipush #40
    //   258: putfield I : I
    //   261: aload_0
    //   262: aload_0
    //   263: getfield I : I
    //   266: putfield J : I
    //   269: return
  }
  
  public void a(String paramString) {
    // Byte code:
    //   0: getstatic JSVenice.b : Z
    //   3: istore #9
    //   5: ldc ''
    //   7: astore_2
    //   8: ldc ''
    //   10: astore_3
    //   11: ldc ''
    //   13: astore #4
    //   15: aload_0
    //   16: new k
    //   19: dup
    //   20: aload_1
    //   21: bipush #10
    //   23: invokespecial <init> : (Ljava/lang/String;C)V
    //   26: putfield Bb : Lk;
    //   29: aload_0
    //   30: getfield Bb : Lk;
    //   33: invokevirtual b : ()I
    //   36: istore #5
    //   38: aload_0
    //   39: new java/util/Vector
    //   42: dup
    //   43: iload #5
    //   45: iconst_5
    //   46: invokespecial <init> : (II)V
    //   49: putfield Cb : Ljava/util/Vector;
    //   52: iconst_0
    //   53: istore #6
    //   55: iload #9
    //   57: ifeq -> 259
    //   60: aload_0
    //   61: getfield Bb : Lk;
    //   64: invokevirtual c : ()Ljava/lang/String;
    //   67: astore_2
    //   68: new k
    //   71: dup
    //   72: aload_2
    //   73: bipush #32
    //   75: invokespecial <init> : (Ljava/lang/String;C)V
    //   78: astore #7
    //   80: aload_3
    //   81: ldc ''
    //   83: if_acmpeq -> 106
    //   86: new java/lang/StringBuffer
    //   89: dup
    //   90: invokespecial <init> : ()V
    //   93: aload_3
    //   94: invokevirtual append : (Ljava/lang/String;)Ljava/lang/StringBuffer;
    //   97: ldc ' '
    //   99: invokevirtual append : (Ljava/lang/String;)Ljava/lang/StringBuffer;
    //   102: invokevirtual toString : ()Ljava/lang/String;
    //   105: astore_3
    //   106: new java/lang/StringBuffer
    //   109: dup
    //   110: invokespecial <init> : ()V
    //   113: aload_3
    //   114: invokevirtual append : (Ljava/lang/String;)Ljava/lang/StringBuffer;
    //   117: aload #7
    //   119: invokevirtual c : ()Ljava/lang/String;
    //   122: invokevirtual append : (Ljava/lang/String;)Ljava/lang/StringBuffer;
    //   125: invokevirtual toString : ()Ljava/lang/String;
    //   128: astore_3
    //   129: aload #7
    //   131: invokevirtual c : ()Ljava/lang/String;
    //   134: astore #4
    //   136: new java/lang/StringBuffer
    //   139: dup
    //   140: invokespecial <init> : ()V
    //   143: aload_3
    //   144: invokevirtual append : (Ljava/lang/String;)Ljava/lang/StringBuffer;
    //   147: ldc ' '
    //   149: invokevirtual append : (Ljava/lang/String;)Ljava/lang/StringBuffer;
    //   152: aload #4
    //   154: invokevirtual append : (Ljava/lang/String;)Ljava/lang/StringBuffer;
    //   157: invokevirtual toString : ()Ljava/lang/String;
    //   160: astore #8
    //   162: aload_0
    //   163: getfield Y : Ljavax/microedition/lcdui/Font;
    //   166: aload #8
    //   168: invokevirtual stringWidth : (Ljava/lang/String;)I
    //   171: aload_0
    //   172: getfield W : I
    //   175: if_icmpge -> 185
    //   178: aload #8
    //   180: astore_3
    //   181: ldc ''
    //   183: astore #4
    //   185: aload #4
    //   187: ldc ''
    //   189: if_acmpne -> 200
    //   192: aload #7
    //   194: invokevirtual a : ()Z
    //   197: ifne -> 129
    //   200: aload_0
    //   201: getfield Cb : Ljava/util/Vector;
    //   204: aload_3
    //   205: invokevirtual addElement : (Ljava/lang/Object;)V
    //   208: aload #7
    //   210: invokevirtual a : ()Z
    //   213: ifne -> 240
    //   216: aload #4
    //   218: ldc ''
    //   220: if_acmpeq -> 240
    //   223: aload_0
    //   224: getfield Cb : Ljava/util/Vector;
    //   227: aload #4
    //   229: invokevirtual addElement : (Ljava/lang/Object;)V
    //   232: ldc ''
    //   234: astore_3
    //   235: iload #9
    //   237: ifeq -> 243
    //   240: aload #4
    //   242: astore_3
    //   243: aload #7
    //   245: invokevirtual a : ()Z
    //   248: ifne -> 129
    //   251: iload #9
    //   253: ifne -> 208
    //   256: iinc #6, 1
    //   259: iload #6
    //   261: iload #5
    //   263: if_icmplt -> 60
    //   266: iload #9
    //   268: ifne -> 68
    //   271: return
  }
  
  void d() {
    // Byte code:
    //   0: getstatic JSVenice.b : Z
    //   3: istore_2
    //   4: aload_0
    //   5: getfield Ob : I
    //   8: invokestatic d : (I)V
    //   11: iconst_0
    //   12: istore_1
    //   13: iload_2
    //   14: ifeq -> 32
    //   17: iload_1
    //   18: iconst_1
    //   19: iadd
    //   20: aload_0
    //   21: getfield w : [Z
    //   24: iload_1
    //   25: baload
    //   26: invokestatic a : (IZ)V
    //   29: iinc #1, 1
    //   32: iload_1
    //   33: iconst_3
    //   34: if_icmplt -> 17
    //   37: iload_2
    //   38: ifne -> 29
    //   41: goto -> 53
    //   44: astore_1
    //   45: getstatic java/lang/System.out : Ljava/io/PrintStream;
    //   48: ldc 'fail update'
    //   50: invokevirtual println : (Ljava/lang/String;)V
    //   53: return
    // Exception table:
    //   from	to	target	type
    //   4	37	44	java/lang/Exception
  }
  
  public String a(InputStream paramInputStream) {
    // Byte code:
    //   0: aconst_null
    //   1: astore_2
    //   2: new java/lang/StringBuffer
    //   5: dup
    //   6: invokespecial <init> : ()V
    //   9: astore_3
    //   10: sipush #512
    //   13: newarray byte
    //   15: astore #4
    //   17: iconst_0
    //   18: istore #5
    //   20: aload_3
    //   21: new java/lang/String
    //   24: dup
    //   25: aload #4
    //   27: iconst_0
    //   28: iload #5
    //   30: invokespecial <init> : ([BII)V
    //   33: invokevirtual append : (Ljava/lang/String;)Ljava/lang/StringBuffer;
    //   36: pop
    //   37: aload_1
    //   38: aload #4
    //   40: invokevirtual read : ([B)I
    //   43: dup
    //   44: istore #5
    //   46: ifgt -> 20
    //   49: getstatic JSVenice.b : Z
    //   52: ifne -> 37
    //   55: goto -> 60
    //   58: astore #6
    //   60: aload_3
    //   61: invokevirtual toString : ()Ljava/lang/String;
    //   64: dup
    //   65: astore_2
    //   66: areturn
    // Exception table:
    //   from	to	target	type
    //   20	49	58	java/lang/Exception
  }
  
  void e() {
    String str = new String(this.rc);
    int i = 1;
    int j = -1;
    try {
      i = Integer.parseInt(this.qc);
      j = Integer.parseInt(str);
    } catch (Exception exception) {}
    this.g[0] = this.a.yb = false;
    a();
  }
}


/* Location:              /home/jknz0/Downloads/MFI_JetSkiVenice_MotorolaT720_Eng_1_0_0.jar!/f.class
 * Java compiler version: 1 (45.3)
 * JD-Core Version:       1.1.3
 */